jemma/__init__.py
jemma/huddle.py
jemma/thinker.py
jemma/tools.py
jemma/prompt/__init__.py
jemma/prompt/business/__init__.py
jemma/prompt/business/owner.py
jemma/prompt/engineer/__init__.py
jemma/prompt/engineer/clarify.py
jemma/prompt/engineer/code.py
jemma/prompt/engineer/game.py
jemma/prompt/tester/__init__.py
jemma/prompt/tester/test.py
jemma/prompt/ui/designer.py
jemma/requirements/__init__.py
jemma/requirements/feature.py
jemma/team/__init__.py
jemma/team/business_owner.py
jemma/team/engineer.py
jemma/team/project_manager.py
jemma/team/tester.py
jemma/team/ui_ux_designer.py
jemma/work/__init__.py
jemma/work/flow.py
jemma-0.1.4207.dist-info/METADATA
jemma-0.1.4207.dist-info/WHEEL
jemma-0.1.4207.dist-info/entry_points.txt
jemma-0.1.4207.dist-info/top_level.txt
jemma-0.1.4207.dist-info/RECORD
