Metadata-Version: 2.1
Name: jemma
Version: 0.1.4207
Summary: jemma & her ai agents that build software
Author: tolitius
Project-URL: Homepage, https://github.com/tolitius/jemma
Project-URL: Documentation, https://github.com/tolitius/jemma?tab=readme-ov-file#-jemma
Project-URL: Repository, https://github.com/tolitius/jemma
Project-URL: Issues, https://github.com/tolitius/jemma/issues
Keywords: ai,agents,llm,code generation
Requires-Dist: python-dotenv ==1.0.1
Requires-Dist: anthropic ==0.21.3
Requires-Dist: openai ==1.14.3
Requires-Dist: ollama ==0.1.8
Requires-Dist: replicate ==0.25.1
Requires-Dist: colalamo ==0.1.2106
Requires-Dist: pyreadline3 ==3.4.1 ; os_name == "nt"
